pycodify/__init__.py
pycodify/core.py
pycodify/formatters.py
pycodify/imports.py
pycodify-0.1.2.dist-info/METADATA
pycodify-0.1.2.dist-info/WHEEL
pycodify-0.1.2.dist-info/licenses/LICENSE
pycodify-0.1.2.dist-info/RECORD
